tenzro/__init__.py
tenzro/jobs.py
tenzro-0.1.0.dist-info/LICENSE
tenzro-0.1.0.dist-info/METADATA
tenzro-0.1.0.dist-info/WHEEL
tenzro-0.1.0.dist-info/top_level.txt
tenzro-0.1.0.dist-info/RECORD
