Metadata-Version: 2.2
Name: tenzro
Version: 0.1.0
Summary: Official Python SDK for Tenzro API
Home-page: https://github.com/tenzro/tenzro-python
Author: Tenzro Team
Author-email: eng@tenzro.com
Classifier: Programming Language :: Python :: 3
Classifier: License :: OSI Approved :: MIT License
Classifier: Operating System :: OS Independent
Requires-Python: >=3.7
License-File: LICENSE
Requires-Dist: aiohttp>=3.8.0
Requires-Dist: pydantic>=2.0.0
Dynamic: author
Dynamic: author-email
Dynamic: classifier
Dynamic: description
Dynamic: description-content-type
Dynamic: home-page
Dynamic: requires-dist
Dynamic: requires-python
Dynamic: summary
